abc_utils/__init__.py
abc_utils/console.py
abc_utils/parallel.py
abc_utils/test_base.py
abc_utils/abc_data/__init__.py
abc_utils/abc_data/abc_data.py
abc_utils/abc_data/feature_utils.py
abc_utils/abc_data/test_abc_data.py
abc_utils/hdf5/__init__.py
abc_utils/hdf5/dataset.py
abc_utils/hdf5/io_struct.py
abc_utils/mesh/__init__.py
abc_utils/mesh/filters.py
abc_utils/mesh/indexing.py
abc_utils/mesh/io.py
abc_utils/torch/__init__.py
abc_utils/torch/transformations.py
abc_utils/torch/transforms.py
abc_utils-0.0.1.dist-info/LICENSE
abc_utils-0.0.1.dist-info/METADATA
abc_utils-0.0.1.dist-info/WHEEL
abc_utils-0.0.1.dist-info/top_level.txt
abc_utils-0.0.1.dist-info/RECORD
